Omega/Omega.py
Omega/__init__.py
omaga_permutation-1.0.0.dist-info/METADATA
omaga_permutation-1.0.0.dist-info/WHEEL
omaga_permutation-1.0.0.dist-info/licenses/LICENSE
omaga_permutation-1.0.0.dist-info/RECORD
