Metadata-Version: 2.1
Name: omaga-permutation
Version: 1.0.0
Summary: Pacote para efetuar permutações de elementos
Project-URL: Homepage, https://github.com/Matheushfb/omega
Project-URL: Bug Tracker, https://github.com/pypa/omega/issues
Author-email: Matheus Brandão <matheushfbrandao@gmail.com>
License-File: LICENSE
Classifier: License :: OSI Approved :: Apache Software License
Classifier: Operating System :: OS Independent
Classifier: Programming Language :: Python :: 3
Requires-Python: >=3.7
